cryptoboxes/__init__.py
cryptoboxes/codes.py
cryptoboxes-0.0.1.dist-info/METADATA
cryptoboxes-0.0.1.dist-info/WHEEL
cryptoboxes-0.0.1.dist-info/top_level.txt
cryptoboxes-0.0.1.dist-info/RECORD
